bb_django_library/__init__.py
bb_django_library/models.py
bb_django_library/utils.py
bb_django_library-0.1.0.dist-info/METADATA
bb_django_library-0.1.0.dist-info/RECORD
bb_django_library-0.1.0.dist-info/WHEEL
bb_django_library-0.1.0.dist-info/top_level.txt
